{
  "gitSyncId": "67c7ef633f2f9833fe5ad1d7_302a6421-3e71-4b10-bab5-de94fef7c37c",
  "id": "Valmistusnumero_JSObject2.iptHaeKeskuksetonSubmit",
  "pluginId": "js-plugin",
  "pluginType": "JS",
  "unpublishedAction": {
    "actionConfiguration": {
      "encodeParamsToggle": true,
      "jsArguments": [],
      "paginationType": "NONE",
      "timeoutInMillisecond": 10000
    },
    "clientSideExecution": true,
    "collectionId": "Valmistusnumero_JSObject2",
    "confirmBeforeExecute": false,
    "datasource": {
      "isAutoGenerated": false,
      "name": "UNUSED_DATASOURCE",
      "pluginId": "js-plugin"
    },
    "dynamicBindingPathList": [
      {
        "key": "body"
      }
    ],
    "executeOnLoad": false,
    "fullyQualifiedName": "JSObject2.iptHaeKeskuksetonSubmit",
    "name": "iptHaeKeskuksetonSubmit",
    "pageId": "Valmistusnumero",
    "userSetOnLoad": false
  }
}